jaxon/__init__.py
jaxon-1.0.2.dist-info/licenses/LICENSE
jaxon-1.0.2.dist-info/METADATA
jaxon-1.0.2.dist-info/WHEEL
jaxon-1.0.2.dist-info/top_level.txt
jaxon-1.0.2.dist-info/RECORD
