Metadata-Version: 2.4
Name: jaxon
Version: 1.0.2
Summary: Save pytrees efficiently in hdf5 files
Author-email: Frank Hermann <frank.c.Hermann@googlemail.com>
Project-URL: Homepage, https://github.com/42Ar/jaxon
Keywords: JAX,Serialization,Equinox,HDF5
Classifier: Programming Language :: Python :: 3
Classifier: Operating System :: OS Independent
License-File: LICENSE
Requires-Dist: numpy
Requires-Dist: jax
Requires-Dist: h5py
Requires-Dist: dill
Dynamic: license-file
